<Tasks ID="666" Name="万圣之夜" AwardMsg="恭喜你获得1个企鹅呆呆（肥肥猪）、2个胖胖浣熊（牧场动物）和10000摩尔豆哦！" AwardBean="">
	<Step ID="1" TarMapID="406">
		<EnterMap MapID="406">
			<Action Cmd="PLAY_MOVIE" Param="1" Name="movie_1" IsBg="1" IsFullScreen="1"/>
			<Action Cmd="DELETE_MOVIE" Param="movie_1"/>
			
			<Action Cmd="JUMP_TASK_UI" Param="变成黑猫的捷克王子让哈哈魔法师把大家接回去了？"/>
			
			<Action Cmd="GO_MAP" MapID="24" MapType="0"/>
			
			<Action Cmd="SET_BUFFER" Panel="2" Step="2"/>
		</EnterMap>
	</Step>
	
	<Step ID="2" TarMapID="24">
		<EnterMap MapID="24">
			<Action Cmd="PLAY_MOVIE" Param="2" Name="movie_2" IsBg="1" IsFullScreen="1"/>
			<Action Cmd="SAY">
				<Talk NpcID="10033" Face="正常" Msg="哎，捷克到最终还是……" Option=""/>
				<Talk NpcID="10307" Face="生气" Msg="捷克……哈哈，有没有办法啊？ " Option=""/>
				<Talk NpcID="10033" Face="正常" Msg="这次仪式失败，摩尔之眼不知去向，女神之泪又没有带回来，我完全没有办法。" Option=""/>
				<Talk NpcID="10307" Face="生气" Msg="只要带回女神之泪就可以吗？ " Option=""/>
				<Talk NpcID="10033" Face="正常" Msg="要摩尔真王带回女神之泪，正式启动王子的净化仪式……" Option=""/>
				<Talk NpcID="10307" Face="生气" Msg="我现在就去！！ " Option=""/>
				<Talk NpcID="10033" Face="正常" Msg="公主作为摩尔真王还没有觉醒，请给她足够的耐心，帮助她成为真王！" Option=""/>
				<Talk NpcID="10307" Face="生气" Msg="恩！ " Option="我也会帮忙的！"/>
			</Action>
			<Action Cmd="DELETE_MOVIE" Param="movie_2"/>
			
			<Action Cmd="PLAY_MOVIE" Param="100" Name="movie_100" IsBg="1" IsFullScreen="1"/>
			<Action Cmd="DELETE_MOVIE" Param="movie_100"/>
			
			<Action Cmd="OVER"/>
		</EnterMap>	
	</Step>
</Tasks>


